naipy/__init__.py
naipy/client.py
naipy/error.py
naipy/http.py
naipy/model.py
naipy/sync.py
naipy-2.5.1.dist-info/License
naipy-2.5.1.dist-info/METADATA
naipy-2.5.1.dist-info/WHEEL
naipy-2.5.1.dist-info/top_level.txt
naipy-2.5.1.dist-info/RECORD
