Metadata-Version: 2.1
Name: naipy
Version: 2.5.1
Summary: 네이버 API를 사용한 검색/번역 라이브러리
Home-page: https://github.com/VoidAsMad/Naipy
Author: VoidAsMad
Author-email: voidasmad@gmail.com
License: MIT
Requires-Python: >=3.6
License-File: License
Requires-Dist: requests
Requires-Dist: aiohttp
